{
  "ticket_id": "h77--xip",
  "agent": "unknown",
  "start_time": "2026-02-27T02:01:55Z",
  "gates": {
    "tsc": {
      "result": "pass",
      "timestamp": "2026-02-27T02:01:55Z"
    },
    "build": {
      "result": "pass",
      "timestamp": "2026-02-27T02:01:55Z"
    },
    "vitest": {
      "result": "pass",
      "timestamp": "2026-02-27T02:01:55Z"
    },
    "mutation": {
      "result": "pass",
      "timestamp": "2026-02-27T02:01:55Z"
    },
    "visual": {
      "result": "pass",
      "timestamp": "2026-02-27T02:01:55Z"
    }
  },
  "census_before": {
    "ts_files": 192,
    "tsx_files": 77,
    "test_files": 110,
    "sh_files": 20
  },
  "census_after": {
    "ts_files": 192,
    "tsx_files": 77,
    "test_files": 110,
    "sh_files": 20
  },
  "census_delta": {
    "ts_files": 0,
    "tsx_files": 0,
    "test_files": 0,
    "sh_files": 0
  },
  "end_time": "2026-02-27T02:01:55Z"
}
